jwtpie.py
jwtpie-1.2.0.dist-info/LICENSE
jwtpie-1.2.0.dist-info/METADATA
jwtpie-1.2.0.dist-info/WHEEL
jwtpie-1.2.0.dist-info/top_level.txt
jwtpie-1.2.0.dist-info/RECORD
