Metadata-Version: 2.1
Name: jwtpie
Version: 1.2.0
Summary: Easily encode and decode JWT tokens
Home-page: https://github.com/kuralabs/jwtpie
Author: KuraLabs S.R.L
Author-email: info@kuralabs.io
License: UNKNOWN
Keywords: jwtpie
Platform: UNKNOWN
Classifier: Development Status :: 4 - Beta
Classifier: Intended Audience :: Developers
Classifier: License :: OSI Approved :: Apache Software License
Classifier: Natural Language :: English
Classifier: Operating System :: POSIX :: Linux
Classifier: Programming Language :: Python :: 3
Requires-Dist: jwcrypto (>=1.4)
